nifty_nesting/__init__.py
nifty_nesting/nifty_nesting.py
nifty_nesting/nifty_nesting_test.py
nifty_nesting/setup.py
nifty_nesting-0.2.3.dist-info/LICENSE
nifty_nesting-0.2.3.dist-info/METADATA
nifty_nesting-0.2.3.dist-info/WHEEL
nifty_nesting-0.2.3.dist-info/top_level.txt
nifty_nesting-0.2.3.dist-info/RECORD
