Metadata-Version: 2.1
Name: nifty-nesting
Version: 0.2.3
Summary: Python utilities for arbitrarily nested data structures.
Home-page: https://github.com/aetiusflavius/nifty-nesting/
Author: Aetius Flavius
Author-email: aetius.flavius.390@gmail.com
License: UNKNOWN
Keywords: nested,data,structure,arbitrary,utilities,manipulation
Platform: UNKNOWN
Classifier: License :: OSI Approved :: MIT License
Classifier: Operating System :: OS Independent
Classifier: Programming Language :: Python :: 2
Classifier: Programming Language :: Python :: 3
Requires-Dist: attrs
Requires-Dist: six
